README.rst
setup.py
html2bbcode/__init__.py
html2bbcode/parser.py
html2bbcode.egg-info/PKG-INFO
html2bbcode.egg-info/SOURCES.txt
html2bbcode.egg-info/dependency_links.txt
html2bbcode.egg-info/top_level.txt
html2bbcode/data/defaults.conf
scripts/html2bbcode