Metadata-Version: 1.1
Name: html2bbcode
Version: 2.3.0
Summary: HTML to BBCode converter
Home-page: https://bitbucket.org/amigo/html2bbcode
Author: Vladimir Korsun
Author-email: korsun.vladimir@gmail.com
License: BSD
Platform: UNKNOWN
Classifier: Topic :: Utilities
Classifier: Topic :: Text Processing :: Markup :: HTML
Classifier: License :: OSI Approved :: BSD License
Classifier: Programming Language :: Python :: 2.7
Classifier: Programming Language :: Python :: 3
